Obfuscratchor/__init__.py
obfuscratchor-2.8.dist-info/licenses/LICENSE
obfuscratchor-2.8.dist-info/METADATA
obfuscratchor-2.8.dist-info/WHEEL
obfuscratchor-2.8.dist-info/top_level.txt
obfuscratchor-2.8.dist-info/RECORD
