Metadata-Version: 2.4
Name: Obfuscratchor
Version: 2.8
Summary: A simple obfuscation tool for Scratch.
Home-page: https://github.com/hackerzoukeyan/Obfuscratchor
Author: JingZhi
Author-email: keyanzou1@gmail.com
License: MIT
Classifier: Programming Language :: Python :: 3
Classifier: License :: OSI Approved :: MIT License
Classifier: Operating System :: OS Independent
License-File: LICENSE
Dynamic: author
Dynamic: author-email
Dynamic: classifier
Dynamic: description
Dynamic: description-content-type
Dynamic: home-page
Dynamic: license
Dynamic: license-file
Dynamic: summary
